Workbook
Name aporte: Planilha1!$H$20
Name qtd_tempo: Planilha1!$H$21
Name rendimento_carteira: Planilha1!$F$15
Name taxa_mensal: Planilha1!$H$22

Sheet Planilha1
D12: CONFIGURAÇÕES
D14: Salário | H14: 4200
D15: Rendimendo Carteira | H15: 0.006
D16: Sugestão de Investimento | H16: 1260
D18: INVESTIMENTO MENSAL
B20: 2 | D20: Quanto investir por mês? | H20: 1260
B21: 5 | D21: Por quantos anos? | H21: 10
B22: 10 | D22: Taxa de Rendimento mensal? | H22: 0.01079
B23: 20 | D23: Quanto de Patrimônio acumulado? | H23: =FV(taxa_mensal,qtd_tempo*12,-aporte) -> 306538.11
B24: 30 | D24: Quano serão os dividendos mensais? | H24: =H23*taxa_mensal -> 3307.5462
D26: CENÁRIO | H26: Dividendo
D28: Quanto em 2 Anos? | G28: =FV($H$22,$B20*12,$H$20*-1) -> 34306.81 | H28: =G28*$H$15 -> 205.84086
D29: Quanto em 5 Anos? | G29: =FV($H$22,$B21*12,$H$20*-1) -> 105558.91 | H29: =G29*$H$15 -> 633.35347
D30: Quanto em 10 Anos? | G30: =FV($H$22,$B22*12,$H$20*-1) -> 306538.11 | H30: =G30*$H$15 -> 1839.2286
D31: Quanto em 20 Anos? | G31: =FV($H$22,$B23*12,$H$20*-1) -> 1417750 | H31: =G31*$H$15 -> 8506.4999
D32: Quanto em 30 Anos? | G32: =FV($H$22,$B24*12,$H$20*-1) -> 5445933.8 | H32: =G32*$H$15 -> 32675.603
D35: PERFIL | G35: Moderado
D36: VALOR A SER INVESTIDO POR MÊS | G36: 500
D38: TIPO DE FII | G38: PERCENTUAL SUGERIDO | H38: VALORES
D39: PAPEL | G39: =VLOOKUP($G$35&"-"&D39,Planilha2!$B$4:$E$22,4,) -> 0.32 | H39: =$G$36*G39 -> 160
D40: TIJOLO | G40: =VLOOKUP($G$35&"-"&D40,Planilha2!$B$4:$E$22,4,) -> 0.35 | H40: =$G$36*G40 -> 175
D41: HÍBRIDOS | G41: =VLOOKUP($G$35&"-"&D41,Planilha2!$B$4:$E$22,4,) -> 0.08 | H41: =$G$36*G41 -> 40
D42: FOFs | G42: =VLOOKUP($G$35&"-"&D42,Planilha2!$B$4:$E$22,4,) -> 0.05 | H42: =$G$36*G42 -> 25
D43: DESENVOLVIMENTO | G43: =VLOOKUP($G$35&"-"&D43,Planilha2!$B$4:$E$22,4,) -> 0.1 | H43: =$G$36*G43 -> 50
D44: HOTELARIAS | G44: =VLOOKUP($G$35&"-"&D44,Planilha2!$B$4:$E$22,4,) -> 0.1 | H44: =$G$36*G44 -> 50
H45: =SUM(H39:H44) -> 500

Sheet Planilha2
B4: CHAVE | C4: PERFIL | D4: TIPO DE PERFIL | E4: % | H4: Chave | I4: %
B5: =C5&"-"&D5 -> Conservador-PAPEL | C5: Conservador | D5: PAPEL | E5: 0.3 | H5: Conservador-TIJOLO | I5: =VLOOKUP(H5,$B$4:$E$22,4,) -> 0.5
B6: =C6&"-"&D6 -> Conservador-TIJOLO | C6: Conservador | D6: TIJOLO | E6: 0.5
B7: =C7&"-"&D7 -> Conservador-HÍBRIDOS | C7: Conservador | D7: HÍBRIDOS | E7: 0.1
B8: =C8&"-"&D8 -> Conservador-FOFs | C8: Conservador | D8: FOFs | E8: 0.1
B9: =C9&"-"&D9 -> Conservador-DESENVOLVIMENTO | C9: Conservador | D9: DESENVOLVIMENTO | E9: 0
B10: =C10&"-"&D10 -> Conservador-HOTELARIAS | C10: Conservador | D10: HOTELARIAS | E10: 0
B11: =C11&"-"&D11 -> Moderado-PAPEL | C11: Moderado | D11: PAPEL | E11: 0.32
B12: =C12&"-"&D12 -> Moderado-TIJOLO | C12: Moderado | D12: TIJOLO | E12: 0.35
B13: =C13&"-"&D13 -> Moderado-HÍBRIDOS | C13: Moderado | D13: HÍBRIDOS | E13: 0.08
B14: =C14&"-"&D14 -> Moderado-FOFs | C14: Moderado | D14: FOFs | E14: 0.05
B15: =C15&"-"&D15 -> Moderado-DESENVOLVIMENTO | C15: Moderado | D15: DESENVOLVIMENTO | E15: 0.1
B16: =C16&"-"&D16 -> Moderado-HOTELARIAS | C16: Moderado | D16: HOTELARIAS | E16: 0.1
B17: =C17&"-"&D17 -> Agressivo-PAPEL | C17: Agressivo | D17: PAPEL | E17: 0.5
... B22: =C22&"-"&D22 -> Agressivo-HOTELARIAS | C22: Agressivo | D22: HOTELARIAS | E22: 0.1
